svgdiagram/REQUIREMENTS
svgdiagram/VERSION
svgdiagram/__init__.py
svgdiagram/derived_elements/__init__.py
svgdiagram/derived_elements/milestone.py
svgdiagram/derived_elements/task.py
svgdiagram/diagrams/__init__.py
svgdiagram/diagrams/gantt/__init__.py
svgdiagram/diagrams/gantt/dependency.py
svgdiagram/diagrams/gantt/fields.py
svgdiagram/diagrams/gantt/gantt.py
svgdiagram/diagrams/gantt/gantt_content.py
svgdiagram/diagrams/gantt/gantt_options.py
svgdiagram/diagrams/gantt/loader.py
svgdiagram/diagrams/gantt/milestone.py
svgdiagram/diagrams/gantt/swimlane.py
svgdiagram/diagrams/gantt/task.py
svgdiagram/diagrams/gantt/utils.py
svgdiagram/diagrams/gantt/renderer/__init__.py
svgdiagram/diagrams/gantt/renderer/swimlane.py
svgdiagram/diagrams/network/__init__.py
svgdiagram/diagrams/network/link.py
svgdiagram/diagrams/network/network.py
svgdiagram/diagrams/network/node.py
svgdiagram/elements/__init__.py
svgdiagram/elements/alignment.py
svgdiagram/elements/circle.py
svgdiagram/elements/defs.py
svgdiagram/elements/group.py
svgdiagram/elements/marker.py
svgdiagram/elements/multi_line_text.py
svgdiagram/elements/path.py
svgdiagram/elements/rect.py
svgdiagram/elements/svg.py
svgdiagram/elements/svg_element.py
svgdiagram/elements/text.py
svgdiagram/shapes/__init__.py
svgdiagram/shapes/anchor.py
svgdiagram/shapes/circular_shape.py
svgdiagram/shapes/connection.py
svgdiagram/shapes/diamond_shape.py
svgdiagram/shapes/shape.py
svgdiagram/shapes/utils.py
svgdiagram/wrappers/__init__.py
svgdiagram/wrappers/wrap_circle.py
svgdiagram/wrappers/wrap_rect.py
svgdiagram-1.5.0.dist-info/LICENSE
svgdiagram-1.5.0.dist-info/METADATA
svgdiagram-1.5.0.dist-info/WHEEL
svgdiagram-1.5.0.dist-info/top_level.txt
svgdiagram-1.5.0.dist-info/RECORD
